plus_slurm/__init__.py
plus_slurm/__version__.py
plus_slurm/job.py
plus_slurm/jobcluster.py
plus_slurm/py.typed
plus_slurm/jinja2_templates/runner.py
plus_slurm/jinja2_templates/submit.sh
plus_slurm-0.3.2.dist-info/METADATA
plus_slurm-0.3.2.dist-info/WHEEL
plus_slurm-0.3.2.dist-info/licenses/LICENSE
plus_slurm-0.3.2.dist-info/RECORD
