Metadata-Version: 2.3
Name: plus_slurm
Version: 0.3.2
Summary: Convenient Python Abstraction for the Slurm based cluster at the PLUS
Author-email: Thomas Hartmann <thomas.hartmann@th-ht.de>
License: GPL-3.0
License-File: LICENSE
Keywords: cluster,slurm
Classifier: Development Status :: 5 - Production/Stable
Classifier: Intended Audience :: Science/Research
Classifier: License :: OSI Approved :: GNU General Public License v3 or later (GPLv3+)
Classifier: Operating System :: OS Independent
Classifier: Programming Language :: Python
Classifier: Typing :: Typed
Requires-Python: >=3.9
Requires-Dist: future
Requires-Dist: humanfriendly
Requires-Dist: jinja2
Requires-Dist: numpy
Requires-Dist: psutil
Requires-Dist: six
